CFileIoDumpDealBase.py
CFileIoDumpDealFlarum.py
CFlarumBase.py
CFlarumJson.py
CFlarumOper.py
calc_match_time.py
control_cron.py
flarum_func.py
fileiodumpdeal-0.1.53.dist-info/METADATA
fileiodumpdeal-0.1.53.dist-info/WHEEL
fileiodumpdeal-0.1.53.dist-info/entry_points.txt
fileiodumpdeal-0.1.53.dist-info/top_level.txt
fileiodumpdeal-0.1.53.dist-info/RECORD
