Metadata-Version: 2.4
Name: FileIoDumpDeal
Version: 0.1.53
Summary: 通过文件IO的方式实现从Flarum获取任务要求并提交执行结果
Requires-Python: >=3.10
Requires-Dist: llmgenjson>=0.1.3
Requires-Dist: python-dotenv>=1.1.0
Requires-Dist: requests>=2.32.3
Requires-Dist: weberfuncs>=0.0.170
